YaBackup/__init__.py
YaBackup/admin.py
YaBackup/apps.py
YaBackup/backup.py
YaBackup/models.py
YaBackup/locale/ru/LC_MESSAGES/django.mo
YaBackup/locale/ru/LC_MESSAGES/django.po
YaBackup/management/__init__.py
YaBackup/management/commands/YaBackup.py
YaBackup/management/commands/__init__.py
YaBackup/migrations/0001_initial.py
YaBackup/migrations/__init__.py
django_yabackup-0.1.2.dist-info/DESCRIPTION.rst
django_yabackup-0.1.2.dist-info/METADATA
django_yabackup-0.1.2.dist-info/RECORD
django_yabackup-0.1.2.dist-info/WHEEL
django_yabackup-0.1.2.dist-info/metadata.json
django_yabackup-0.1.2.dist-info/top_level.txt
