Metadata-Version: 2.0
Name: django-yabackup
Version: 0.1.2
Summary: A simple Django app to backup your files and database to Yandex.Disk
Home-page: https://github.com/lovelydev/django-yabackup/
Author: Kirill Tsurkan
Author-email: kirilltsurkan@@gmail.com
License: MIT License
Keywords: Yandex.Disk backup
Platform: UNKNOWN
Classifier: Development Status :: 3 - Alpha
Classifier: Environment :: Web Environment
Classifier: Framework :: Django
Classifier: Framework :: Django :: 1.11
Classifier: Intended Audience :: Developers
Classifier: License :: OSI Approved :: MIT License
Classifier: Operating System :: OS Independent
Classifier: Programming Language :: Python
Classifier: Programming Language :: Python :: 3
Classifier: Programming Language :: Python :: 3.4
Classifier: Programming Language :: Python :: 3.5
Classifier: Topic :: Internet :: WWW/HTTP
Classifier: Topic :: Internet :: WWW/HTTP :: Dynamic Content
Requires-Dist: Django (>=1.11)
Requires-Dist: YaDiskClient (>=0.4.5)
